{
    "_description": "White bread — Phase 2 digestion trials. All 3 trials in this file. White bread is also the normalization reference run simultaneously in every other food's session, but these are the standalone white bread sessions where white bread is both food and reference (expected normalized AUC = 100.0).",

    "food_name": "white bread",
    "brand": "",
    "carb_content_per_100g": null,
    "target_carb_g": null,
    "calculated_mass_g": null,
    "_mass_note": "Filled in after Phase 1 mass-finding calibration.",

    "published_gi_value": 100,
    "_gi_note": "White bread GI = 100 by convention (normalization reference).",

    "trial_1": {
        "date": "",
        "buffer_pH": null,
        "water_bath_temp_start_C": null,
        "water_bath_temp_end_C": null,
        "notes": "",
        "food_readings_mA":  [null, null, null, null, null],
        "bread_readings_mA": [null, null, null, null, null]
    },
    "trial_2": {
        "date": "",
        "buffer_pH": null,
        "water_bath_temp_start_C": null,
        "water_bath_temp_end_C": null,
        "notes": "",
        "food_readings_mA":  [null, null, null, null, null],
        "bread_readings_mA": [null, null, null, null, null]
    },
    "trial_3": {
        "date": "",
        "buffer_pH": null,
        "water_bath_temp_start_C": null,
        "water_bath_temp_end_C": null,
        "notes": "",
        "food_readings_mA":  [null, null, null, null, null],
        "bread_readings_mA": [null, null, null, null, null]
    },

    "_readings_note": "Readings order matches experiment_constants.json digestion_time_points_min: [0, 15, 30, 60, 120]."
}
